{"id":"wghdytgfyphqrrcmgp3ko0h","title":"Linter","desc":"","updated":1646862692439,"created":1646862692439,"custom":{},"fname":"tags.linter","type":"note","vault":{"fsPath":"vault"},"contentHash":"c3e6319acbbfd7ce9d2351da7e8bad21","links":[{"from":{"fname":"handbook.golang.4-setup-golang-ci","id":"7hpir84idoztmofa72t2ozc","vaultName":"vault"},"type":"backlink","position":{"start":{"line":2,"column":5,"offset":5},"end":{"line":2,"column":12,"offset":12},"indent":[]},"value":"tags.linter"}],"anchors":{},"children":[],"parent":"u3lhhpriar8wgcjw8svapha","data":{}}
